examples/__init__.py
examples/sauce_demo.py
examples/tests/__init__.py
examples/tests/conftest.py
examples/tests/pytest_headless.py
examples/tests/test_sauce_demo.py
examples/tests/pages/__init__.py
examples/tests/pages/inventory_page.py
examples/tests/pages/login_page.py
locatai/__init__.py
locatai/ai/__init__.py
locatai/ai/prompts/__init__.py
locatai/ai/prompts/locator_prompts.py
locatai/ai/providers/__init__.py
locatai/ai/providers/anthropic_provider.py
locatai/ai/providers/base_provider.py
locatai/ai/providers/openai_provider.py
locatai/cache/__init__.py
locatai/finder/__init__.py
locatai/finder/element_finder.py
locatai/utils/__init__.py
locatai/utils/analytics.py
locatai-0.1.8.dist-info/METADATA
locatai-0.1.8.dist-info/WHEEL
locatai-0.1.8.dist-info/top_level.txt
locatai-0.1.8.dist-info/RECORD
