Metadata-Version: 2.4
Name: locatai
Version: 0.1.8
Summary: AI-powered element locator for Selenium WebDriver
Home-page: https://github.com/Divyarajsinh-Dodia/locatai
Author: LocatAI Team
Author-email: divyarajsinh.dodia@outlook.com
Project-URL: Bug Reports, https://github.com/Divyarajsinh-Dodia/locatai/issues
Project-URL: Source, https://github.com/Divyarajsinh-Dodia/locatai
Project-URL: Documentation, https://github.com/Divyarajsinh-Dodia/locatai/blob/main/README.md
Keywords: selenium,testing,automation,ai,openai,anthropic,claude,test-automation,webdriver,locator,element-finding
Classifier: Development Status :: 4 - Beta
Classifier: Intended Audience :: Developers
Classifier: Topic :: Software Development :: Testing
Classifier: License :: OSI Approved :: MIT License
Classifier: Programming Language :: Python :: 3
Classifier: Programming Language :: Python :: 3.8
Classifier: Programming Language :: Python :: 3.9
Classifier: Programming Language :: Python :: 3.10
Classifier: Programming Language :: Python :: 3.11
Classifier: Programming Language :: Python :: 3.12
Classifier: Programming Language :: Python :: 3.13
Requires-Python: >=3.8
Requires-Dist: selenium>=4.0.0
Requires-Dist: openai>=1.0.0
Requires-Dist: anthropic>=0.18.0
Requires-Dist: python-dotenv>=0.19.0
Dynamic: author
Dynamic: author-email
Dynamic: classifier
Dynamic: description
Dynamic: description-content-type
Dynamic: home-page
Dynamic: keywords
Dynamic: project-url
Dynamic: requires-dist
Dynamic: requires-python
Dynamic: summary
